graphdb/__init__.py
graphdb/graphdb_workbench/__init__.py
graphdb/graphdb_workbench/api/__init__.py
graphdb/graphdb_workbench/api/cluster_management_controller_api.py
graphdb/graphdb_workbench/api/import_controller_api.py
graphdb/graphdb_workbench/api/location_management_controller_api.py
graphdb/graphdb_workbench/api/repository_management_controller_api.py
graphdb/graphdb_workbench/api/saved_queries_controller_api.py
graphdb/graphdb_workbench/api/security_management_controller_api.py
graphdb/graphdb_workbench/api/sparql_template_controller_api.py
graphdb/graphdb_workbench/api/sql_views_controller_api.py
graphdb/graphdb_workbench/api/stateless_login_controller_api.py
graphdb/graphdb_workbench/api_client.py
graphdb/graphdb_workbench/configuration.py
graphdb/graphdb_workbench/models/__init__.py
graphdb/graphdb_workbench/models/access_bean.py
graphdb/graphdb_workbench/models/account.py
graphdb/graphdb_workbench/models/default_repository_location.py
graphdb/graphdb_workbench/models/graph_db_repository.py
graphdb/graphdb_workbench/models/import_settings.py
graphdb/graphdb_workbench/models/location.py
graphdb/graphdb_workbench/models/location_uri.py
graphdb/graphdb_workbench/models/master_connect_bean.py
graphdb/graphdb_workbench/models/master_node.py
graphdb/graphdb_workbench/models/owlim_parameter.py
graphdb/graphdb_workbench/models/parser_settings.py
graphdb/graphdb_workbench/models/repository_config_bean.py
graphdb/graphdb_workbench/models/repository_size_info.py
graphdb/graphdb_workbench/models/saved_query.py
graphdb/graphdb_workbench/models/server_import_body.py
graphdb/graphdb_workbench/models/sparql_template.py
graphdb/graphdb_workbench/models/sql_column.py
graphdb/graphdb_workbench/models/sql_view.py
graphdb/graphdb_workbench/models/updated_location.py
graphdb/graphdb_workbench/models/user_details.py
graphdb/graphdb_workbench/models/worker_clone_bean.py
graphdb/graphdb_workbench/models/worker_connect_bean.py
graphdb/graphdb_workbench/models/worker_node.py
graphdb_python-0.0.6.dist-info/WHEEL
graphdb_python-0.0.6.dist-info/METADATA
graphdb_python-0.0.6.dist-info/RECORD
