Metadata-Version: 2.1
Name: graphdb python
Version: 0.0.6
Summary: GraphDB Python
Author: Plamen Tarkalanov
Author-email: plamen.tarkalanov@ontotext.com
Requires-Python: >=3.7,<4.0
Classifier: Programming Language :: Python :: 3
Classifier: Programming Language :: Python :: 3.10
Classifier: Programming Language :: Python :: 3.7
Classifier: Programming Language :: Python :: 3.8
Classifier: Programming Language :: Python :: 3.9
Requires-Dist: json-stream (==1.3.0)
Requires-Dist: requests (>=2.27.1,<3.0.0)
Requires-Dist: swagger-to (==4.1.1)
